{"_type":"export","__export_format":4,"__export_date":"2019-06-19T22:25:58.419Z","__export_source":"insomnia.desktop.app:v6.5.4","resources":[{"_id":"req_506460fda0a545f4bc9e83d92405d454","authentication":{},"body":{"mimeType":"application/json","text":"{\n\t\"email\":\"22@email.com\",\n\t\"password\": \"123456\"\n}"},"created":1560982056933,"description":"","headers":[{"id":"pair_081d954424454c3fa941768d858e46fa","name":"Content-Type","value":"application/json"}],"isPrivate":false,"metaSortKey":-1560982056933,"method":"POST","modified":1560982403047,"name":"Login","parameters":[],"parentId":"fld_624d377f2e284ca4b830e67702859c38","settingDisableRenderRequestBody":false,"settingEncodeUrl":true,"settingRebuildPath":true,"settingSendCookies":true,"settingStoreCookies":true,"url":"{{ base_url  }}/api/session","_type":"request"},{"_id":"fld_624d377f2e284ca4b830e67702859c38","created":1560982043356,"description":"","environment":{},"environmentPropertyOrder":null,"metaSortKey":-1560982043356,"modified":1560982043356,"name":"Login","parentId":"fld_528abc28325844fbbf57955412185315","_type":"request_group"},{"_id":"fld_528abc28325844fbbf57955412185315","created":1560784324789,"description":"","environment":{},"environmentPropertyOrder":null,"metaSortKey":-1560784324789,"modified":1560784324789,"name":"Sequelize","parentId":"wrk_15adf16a2b6543d7b2ae2da0dc9ad521","_type":"request_group"},{"_id":"wrk_15adf16a2b6543d7b2ae2da0dc9ad521","created":1551697566869,"description":"","modified":1551697566869,"name":"Insomnia","parentId":null,"_type":"workspace"},{"_id":"req_7755c560c7dd4bf19939f6f2fb800b63","authentication":{},"body":{"mimeType":"multipart/form-data","params":[{"id":"pair_ac701fd0d8b443138cf58dd83ed40a13","name":"name","value":"joao"},{"disabled":false,"id":"pair_af40ff1f340441fcb5cb5399422b9970","name":"perfil_id","value":"1"},{"id":"pair_5df3e96cc434480fb9f4913cfb6769fb","name":"email","value":"22@email.com"},{"id":"pair_3f6e0831a5c64f219654e5d8616d1425","name":"password","value":"123456"},{"id":"pair_212b0b1e96824f2dae0b650ebaf03823","name":"provider","value":"1"},{"disabled":false,"fileName":"C:\\DADOS\\OneDrive\\DB1\\Documentos\\Imagens\\buddy_jesus.jpg","id":"pair_6000acc0afff4edca55b26b519041ea7","name":"avatar","type":"file","value":""}]},"created":1560786188900,"description":"","headers":[{"id":"pair_b6afc33f19ff42caa0e51325b0eb7f9a","name":"Content-Type","value":"multipart/form-data"}],"isPrivate":false,"metaSortKey":-1560786188900,"method":"POST","modified":1560899073625,"name":"Post","parameters":[],"parentId":"fld_1dadf827d57e40ef85e3825a54d50cfb","settingDisableRenderRequestBody":false,"settingEncodeUrl":true,"settingRebuildPath":true,"settingSendCookies":true,"settingStoreCookies":true,"url":"localhost:8080/api/user","_type":"request"},{"_id":"fld_1dadf827d57e40ef85e3825a54d50cfb","created":1560784342192,"description":"","environment":{},"environmentPropertyOrder":null,"metaSortKey":-1560784342192,"modified":1560784342192,"name":"User","parentId":"fld_528abc28325844fbbf57955412185315","_type":"request_group"},{"_id":"req_acf67ee454b545c6b563f7508f5e9add","authentication":{},"body":{"mimeType":"application/json","text":"{\n\t\"name\": \"outro nome\",\n\t\"perfil_id\": 2\n}"},"created":1560786816168,"description":"","headers":[{"id":"pair_b6afc33f19ff42caa0e51325b0eb7f9a","name":"Content-Type","value":"application/json"}],"isPrivate":false,"metaSortKey":-1560785951065,"method":"PUT","modified":1560980493599,"name":"Update","parameters":[],"parentId":"fld_1dadf827d57e40ef85e3825a54d50cfb","settingDisableRenderRequestBody":false,"settingEncodeUrl":true,"settingRebuildPath":true,"settingSendCookies":true,"settingStoreCookies":true,"url":"{{ base_url  }}/api/user/1","_type":"request"},{"_id":"req_5e919aa509ed4af88897582261037272","authentication":{},"body":{},"created":1560785713230,"description":"","headers":[],"isPrivate":false,"metaSortKey":-1560785713230,"method":"GET","modified":1560982829724,"name":"get id","parameters":[],"parentId":"fld_1dadf827d57e40ef85e3825a54d50cfb","settingDisableRenderRequestBody":false,"settingEncodeUrl":true,"settingRebuildPath":true,"settingSendCookies":true,"settingStoreCookies":true,"url":"{{ base_url  }}/api/user/2","_type":"request"},{"_id":"req_890cb3db7ddd4ca7ae910591bc7d0725","authentication":{},"body":{},"created":1560784337374,"description":"","headers":[],"isPrivate":false,"metaSortKey":-1560784337374,"method":"GET","modified":1560810635602,"name":"Get","parameters":[],"parentId":"fld_1dadf827d57e40ef85e3825a54d50cfb","settingDisableRenderRequestBody":false,"settingEncodeUrl":true,"settingRebuildPath":true,"settingSendCookies":true,"settingStoreCookies":true,"url":"{{ base_url  }}/api/user","_type":"request"},{"_id":"req_4b45759d15814fcea4d3af9613b3de52","authentication":{},"body":{},"created":1560980853665,"description":"","headers":[],"isPrivate":false,"metaSortKey":-1560980853665,"method":"DELETE","modified":1560981586528,"name":"Delete","parameters":[],"parentId":"fld_486b8cd9095a408fb6d1ec39289d16e1","settingDisableRenderRequestBody":false,"settingEncodeUrl":true,"settingRebuildPath":true,"settingSendCookies":true,"settingStoreCookies":true,"url":"{{ base_url  }}/api/perfil/5","_type":"request"},{"_id":"fld_486b8cd9095a408fb6d1ec39289d16e1","created":1560809444348,"description":"","environment":{},"environmentPropertyOrder":null,"metaSortKey":-1560784333490.5,"modified":1560809483684,"name":"Perfil","parentId":"fld_528abc28325844fbbf57955412185315","_type":"request_group"},{"_id":"req_86448c248178434d9913bc0416248c7c","authentication":{},"body":{"mimeType":"application/json","text":"{\n\t\"name\": \"Visitante\"\n}"},"created":1560809444367,"description":"","headers":[{"id":"pair_b6afc33f19ff42caa0e51325b0eb7f9a","name":"Content-Type","value":"application/json"}],"isPrivate":false,"metaSortKey":-1560786188900,"method":"POST","modified":1560979068741,"name":"Post","parameters":[],"parentId":"fld_486b8cd9095a408fb6d1ec39289d16e1","settingDisableRenderRequestBody":false,"settingEncodeUrl":true,"settingRebuildPath":true,"settingSendCookies":true,"settingStoreCookies":true,"url":"{{ base_url  }}/api/perfil","_type":"request"},{"_id":"req_025e5b9ecf754fdaa0c2d21c41b23439","authentication":{},"body":{"mimeType":"application/json","text":"{\n\t\"name\": \"Administrador\"\n}"},"created":1560809444370,"description":"","headers":[{"id":"pair_b6afc33f19ff42caa0e51325b0eb7f9a","name":"Content-Type","value":"application/json"}],"isPrivate":false,"metaSortKey":-1560785951065,"method":"PUT","modified":1560980825270,"name":"Update","parameters":[],"parentId":"fld_486b8cd9095a408fb6d1ec39289d16e1","settingDisableRenderRequestBody":false,"settingEncodeUrl":true,"settingRebuildPath":true,"settingSendCookies":true,"settingStoreCookies":true,"url":"{{ base_url  }}/api/perfil/1","_type":"request"},{"_id":"req_780f0675179a47059e3a4fb56f41df72","authentication":{},"body":{},"created":1560809444364,"description":"","headers":[],"isPrivate":false,"metaSortKey":-1560785713230,"method":"GET","modified":1560979077973,"name":"get id","parameters":[],"parentId":"fld_486b8cd9095a408fb6d1ec39289d16e1","settingDisableRenderRequestBody":false,"settingEncodeUrl":true,"settingRebuildPath":true,"settingSendCookies":true,"settingStoreCookies":true,"url":"{{ base_url  }}/api/perfil/2","_type":"request"},{"_id":"req_11f06b3648034913bd692322690d8aa6","authentication":{},"body":{},"created":1560809444360,"description":"","headers":[],"isPrivate":false,"metaSortKey":-1560784337374,"method":"GET","modified":1560810504078,"name":"Get","parameters":[],"parentId":"fld_486b8cd9095a408fb6d1ec39289d16e1","settingDisableRenderRequestBody":false,"settingEncodeUrl":true,"settingRebuildPath":true,"settingSendCookies":true,"settingStoreCookies":true,"url":"{{ base_url  }}/api/perfil","_type":"request"},{"_id":"req_e1692ed80f2344a7bb53ed073921b97d","authentication":{},"body":{"mimeType":"application/json","text":"{\n\t\"email\": \"italo.souza@db1.com.br\",\n\t\"password\":\"rm233gyv33\"\n}"},"created":1551697674200,"description":"","headers":[{"id":"pair_ec8540ae4d994b448932f9524e811407","name":"Content-Type","value":"application/json"}],"isPrivate":false,"metaSortKey":-1551697674200,"method":"POST","modified":1553802065869,"name":"login","parameters":[],"parentId":"fld_0c87fcbcec0a4886a1223eea52e27c0f","settingDisableRenderRequestBody":false,"settingEncodeUrl":true,"settingRebuildPath":true,"settingSendCookies":true,"settingStoreCookies":true,"url":"{{ base_url  }}/session","_type":"request"},{"_id":"fld_0c87fcbcec0a4886a1223eea52e27c0f","created":1551713403226,"description":"","environment":{},"environmentPropertyOrder":null,"metaSortKey":-1551715332780,"modified":1560784306936,"name":"users","parentId":"fld_41189bd9e69d4e72aa63a0ce0c69c5fc","_type":"request_group"},{"_id":"fld_41189bd9e69d4e72aa63a0ce0c69c5fc","created":1560784300918,"description":"","environment":{},"environmentPropertyOrder":null,"metaSortKey":-1560784300918,"modified":1560784300918,"name":"vmQueue","parentId":"wrk_15adf16a2b6543d7b2ae2da0dc9ad521","_type":"request_group"},{"_id":"req_f6bd60ce0dff45ab80b4b8f409e74b53","authentication":{},"body":{"mimeType":"multipart/form-data","params":[{"id":"pair_880d44de7cf4463886df36718675a0b5","name":"name","value":"0001"},{"disabled":false,"id":"pair_e41e4c88ae014ff1a1c5cf9504c3ca4d","name":"email","value":"0001@db1.com.br"},{"disabled":false,"id":"pair_9a4eabc511ee4780af68987fb5973043","name":"password","value":"123456"},{"fileName":"C:\\DADOS\\OneDrive\\DB1\\Documentos\\Imagens\\johnny-five.jpg","id":"pair_647d7e914140488c8e67128adee7309d","name":"avatar","type":"file","value":""}]},"created":1551697578575,"description":"","headers":[{"id":"pair_5b9193a9f6ce4db6b0ff7e9ca2905926","name":"Content-Type","value":"multipart/form-data"}],"isPrivate":false,"metaSortKey":-1551697674150,"method":"POST","modified":1554133228034,"name":"create user","parameters":[],"parentId":"fld_0c87fcbcec0a4886a1223eea52e27c0f","settingDisableRenderRequestBody":false,"settingEncodeUrl":true,"settingRebuildPath":true,"settingSendCookies":true,"settingStoreCookies":true,"url":"{{ base_url  }}/user","_type":"request"},{"_id":"req_cf6ed2a28ce641509bb15935d7bfef1e","authentication":{"token":"{{ token  }}","type":"bearer"},"body":{},"created":1551713627402,"description":"","headers":[],"isPrivate":false,"metaSortKey":-1551713627402,"method":"GET","modified":1551713650003,"name":"get vm","parameters":[],"parentId":"fld_19e1b1029b9f40fd845178867dc692a0","settingDisableRenderRequestBody":false,"settingEncodeUrl":true,"settingRebuildPath":true,"settingSendCookies":true,"settingStoreCookies":true,"url":"localhost:3000/vm/5c7d444ee17fb20b54a02da6","_type":"request"},{"_id":"fld_19e1b1029b9f40fd845178867dc692a0","created":1551713396123,"description":"","environment":{},"environmentPropertyOrder":null,"metaSortKey":-1551715332755,"modified":1560784308693,"name":"vm","parentId":"fld_41189bd9e69d4e72aa63a0ce0c69c5fc","_type":"request_group"},{"_id":"req_160b45b67c174b3a99b51872c2fa4a7d","authentication":{"token":"{{ token  }}","type":"bearer"},"body":{},"created":1551713419609,"description":"","headers":[],"isPrivate":false,"metaSortKey":-1551713267068,"method":"GET","modified":1553802170751,"name":"list vm","parameters":[],"parentId":"fld_19e1b1029b9f40fd845178867dc692a0","settingDisableRenderRequestBody":false,"settingEncodeUrl":true,"settingRebuildPath":true,"settingSendCookies":true,"settingStoreCookies":true,"url":"{{ base_url  }}/vm","_type":"request"},{"_id":"req_ea490eff81df4b728138be92bea48f4e","authentication":{"token":"{{ token  }}","type":"bearer"},"body":{"mimeType":"application/json","text":"{\n\t\"name\": \"253\",\n\t\"description\": \"maquina virtual 253\",\n\t\"ip\":\"127.0.0.3\",\n\t\"available\": false\n}"},"created":1551713267018,"description":"","headers":[{"id":"pair_8810faee62854e3cb17a4966ca9ea3b8","name":"Content-Type","value":"application/json"}],"isPrivate":false,"metaSortKey":-1551713267018,"method":"POST","modified":1552572512086,"name":"create vm","parameters":[],"parentId":"fld_19e1b1029b9f40fd845178867dc692a0","settingDisableRenderRequestBody":false,"settingEncodeUrl":true,"settingRebuildPath":true,"settingSendCookies":true,"settingStoreCookies":true,"url":"localhost:3000/vm","_type":"request"},{"_id":"req_628e673c6d314b4c979fa04f5ece5e1a","authentication":{"token":"{{ token  }}","type":"bearer"},"body":{},"created":1551713676806,"description":"","headers":[],"isPrivate":false,"metaSortKey":-1551713266968,"method":"POST","modified":1551885337592,"name":"join vm","parameters":[],"parentId":"fld_19e1b1029b9f40fd845178867dc692a0","settingDisableRenderRequestBody":false,"settingEncodeUrl":true,"settingRebuildPath":true,"settingSendCookies":true,"settingStoreCookies":true,"url":"localhost:3000/vm/join/5c7d444ee17fb20b54a02da6","_type":"request"},{"_id":"req_3529381152ea4767b537701e97d760f5","authentication":{"token":"{{ token  }}","type":"bearer"},"body":{},"created":1551713814058,"description":"","headers":[],"isPrivate":false,"metaSortKey":-1551713266918,"method":"POST","modified":1552572312169,"name":"leave vm","parameters":[],"parentId":"fld_19e1b1029b9f40fd845178867dc692a0","settingDisableRenderRequestBody":false,"settingEncodeUrl":true,"settingRebuildPath":true,"settingSendCookies":true,"settingStoreCookies":true,"url":"localhost:3000/vm/leave/5c7d44bfe17fb20b54a02da7","_type":"request"},{"_id":"req_9b1b8f36db1148af90bfc8a068a10b89","authentication":{"token":"{{ token  }}","type":"bearer"},"body":{},"created":1551715647394,"description":"","headers":[],"isPrivate":false,"metaSortKey":-1551715647394,"method":"POST","modified":1553802202308,"name":"leave","parameters":[],"parentId":"fld_7631757c729c4fcba90cd5531d8eca82","settingDisableRenderRequestBody":false,"settingEncodeUrl":true,"settingRebuildPath":true,"settingSendCookies":true,"settingStoreCookies":true,"url":"{{ base_url  }}/queue/leave","_type":"request"},{"_id":"fld_7631757c729c4fcba90cd5531d8eca82","created":1551715332730,"description":"","environment":{},"environmentPropertyOrder":null,"metaSortKey":-1551715332730,"modified":1560784304779,"name":"Queue","parentId":"fld_41189bd9e69d4e72aa63a0ce0c69c5fc","_type":"request_group"},{"_id":"req_ce5a8d0f395046abbda60672cc6587b4","authentication":{"token":"{{ token  }}","type":"bearer"},"body":{},"created":1551715385906,"description":"","headers":[],"isPrivate":false,"metaSortKey":-1551715385906,"method":"POST","modified":1551715410171,"name":"join","parameters":[],"parentId":"fld_7631757c729c4fcba90cd5531d8eca82","settingDisableRenderRequestBody":false,"settingEncodeUrl":true,"settingRebuildPath":true,"settingSendCookies":true,"settingStoreCookies":true,"url":"localhost:3000/queue/join","_type":"request"},{"_id":"req_f266e4dedaa448af8d982e80d8a5a77d","authentication":{"token":"{{ token  }}","type":"bearer"},"body":{},"created":1551715349050,"description":"","headers":[],"isPrivate":false,"metaSortKey":-1551715349050,"method":"GET","modified":1553802181998,"name":"list","parameters":[],"parentId":"fld_7631757c729c4fcba90cd5531d8eca82","settingDisableRenderRequestBody":false,"settingEncodeUrl":true,"settingRebuildPath":true,"settingSendCookies":true,"settingStoreCookies":true,"url":"{{ base_url  }}/queue","_type":"request"},{"_id":"env_e9c1748de9dd47d290d3388e55453bb3","color":null,"created":1551697566900,"data":{"base_url":"http://localhost:8080","token":"eyJhbGciOiJIUzI1NiIsInR5cCI6IkpXVCJ9.eyJpZCI6IjVjYTIzMjY1MjRmYWRhMDAyN2YzMjk3MCIsImlhdCI6MTU1NDEzOTg4MSwiZXhwIjoxNTU0MjI2MjgxfQ.HXUc27P3dzJ_uBheuqguqGH2kAjO1Y0pFc8j7FxlUMA"},"dataPropertyOrder":null,"isPrivate":false,"metaSortKey":1551697566900,"modified":1560786069990,"name":"New Environment","parentId":"wrk_15adf16a2b6543d7b2ae2da0dc9ad521","_type":"environment"},{"_id":"jar_a8a59add8ef845e7ac1ff2e39ed46697","cookies":[{"creation":"2019-06-18T22:19:10.633Z","domain":"localhost","hostOnly":true,"httpOnly":true,"id":"32736011211205396","key":"root","lastAccessed":"2019-06-18T22:19:10.633Z","path":"/","value":"s%3AUakyH8xBqjvxsPCGjc56SWuZa1ZCFShn.fN6nSNL4V4ZSLX%2F1V%2FaTDVVDqmJz%2B1%2BPstCipu%2BKy4c"}],"created":1551697566903,"modified":1560896350633,"name":"Default Jar","parentId":"wrk_15adf16a2b6543d7b2ae2da0dc9ad521","_type":"cookie_jar"}]}